[{"first_name":"Margaretta","last_name":"Kryszkiecicz","email":"mkryszkiecicz0@imageshack.us"},
{"first_name":"Cathleen","last_name":"Legion","email":"clegion1@yahoo.com"},
{"first_name":"Jocelyne","last_name":"Stampe","email":"jstampe2@cdbaby.com"},
{"first_name":"Winifield","last_name":"Mallaby","email":"wmallaby3@jalbum.net"},
{"first_name":"Batholomew","last_name":"Arnhold","email":"barnhold4@prweb.com"},
{"first_name":"Suzy","last_name":"Shapter","email":"sshapter5@dmoz.org"},
{"first_name":"Sibyl","last_name":"McCourtie","email":"smccourtie6@miibeian.gov.cn"},
{"first_name":"Charmion","last_name":"Rawdall","email":"crawdall7@opensource.org"},
{"first_name":"Bibi","last_name":"Kenwright","email":"bkenwright8@alibaba.com"},
{"first_name":"Claudell","last_name":"Syrie","email":"csyrie9@nhs.uk"},
{"first_name":"Bayard","last_name":"Ravilus","email":"bravilusa@squarespace.com"},
{"first_name":"Nanny","last_name":"Hubbuck","email":"nhubbuckb@theglobeandmail.com"},
{"first_name":"Isidor","last_name":"Gowland","email":"igowlandc@usatoday.com"},
{"first_name":"Nevile","last_name":"Dunkerk","email":"ndunkerkd@yale.edu"},
{"first_name":"Toni","last_name":"Daveley","email":"tdaveleye@gov.uk"},
{"first_name":"Pennie","last_name":"Arnald","email":"parnaldf@gravatar.com"},
{"first_name":"Ulick","last_name":"Greenley","email":"ugreenleyg@cisco.com"},
{"first_name":"Foster","last_name":"Shedd","email":"fsheddh@arstechnica.com"},
{"first_name":"Nick","last_name":"Bootland","email":"nbootlandi@desdev.cn"},
{"first_name":"Kevan","last_name":"Commings","email":"kcommingsj@ucoz.com"},
{"first_name":"Faulkner","last_name":"Houseman","email":"fhousemank@bloomberg.com"},
{"first_name":"Guillema","last_name":"Spellissy","email":"gspellissyl@github.com"},
{"first_name":"Worden","last_name":"Waterstone","email":"wwaterstonem@usatoday.com"},
{"first_name":"Myrvyn","last_name":"Seeman","email":"mseemann@utexas.edu"},
{"first_name":"Romona","last_name":"Weymouth","email":"rweymoutho@yale.edu"},
{"first_name":"Kahaleel","last_name":"Fitchet","email":"kfitchetp@bbc.co.uk"},
{"first_name":"Alysa","last_name":"Cornew","email":"acornewq@issuu.com"},
{"first_name":"Pincas","last_name":"Dowe","email":"pdower@about.com"},
{"first_name":"Angelica","last_name":"Follos","email":"afolloss@dyndns.org"},
{"first_name":"Floyd","last_name":"Babe","email":"fbabet@hubpages.com"},
{"first_name":"Justinn","last_name":"Vedishchev","email":"jvedishchevu@yale.edu"},
{"first_name":"Pauly","last_name":"Pudan","email":"ppudanv@fema.gov"},
{"first_name":"Drusilla","last_name":"Lowthian","email":"dlowthianw@reverbnation.com"},
{"first_name":"Mord","last_name":"Blatcher","email":"mblatcherx@vimeo.com"},
{"first_name":"Annecorinne","last_name":"Mucklo","email":"amuckloy@weather.com"},
{"first_name":"Rosco","last_name":"Laity","email":"rlaityz@netlog.com"},
{"first_name":"Eloisa","last_name":"Turford","email":"eturford10@yellowpages.com"},
{"first_name":"Izak","last_name":"Hobben","email":"ihobben11@uol.com.br"},
{"first_name":"Kacy","last_name":"Trowsdall","email":"ktrowsdall12@ca.gov"},
{"first_name":"Lemar","last_name":"Bothen","email":"lbothen13@princeton.edu"},
{"first_name":"Cathlene","last_name":"Spatoni","email":"cspatoni14@springer.com"},
{"first_name":"Rochella","last_name":"Gudge","email":"rgudge15@sun.com"},
{"first_name":"Giselbert","last_name":"Atling","email":"gatling16@psu.edu"},
{"first_name":"Selie","last_name":"Greneham","email":"sgreneham17@vinaora.com"},
{"first_name":"Lyndsey","last_name":"Niese","email":"lniese18@google.de"},
{"first_name":"Flore","last_name":"Parkyn","email":"fparkyn19@histats.com"},
{"first_name":"Tarra","last_name":"Mabe","email":"tmabe1a@furl.net"},
{"first_name":"Roseanne","last_name":"Elnaugh","email":"relnaugh1b@dailymotion.com"},
{"first_name":"Ainslee","last_name":"Giller","email":"agiller1c@ehow.com"},
{"first_name":"Melodee","last_name":"Schanke","email":"mschanke1d@hc360.com"},
{"first_name":"Adina","last_name":"Skurm","email":"askurm1e@macromedia.com"},
{"first_name":"Clark","last_name":"Malins","email":"cmalins1f@sohu.com"},
{"first_name":"Celie","last_name":"Duerden","email":"cduerden1g@themeforest.net"},
{"first_name":"Hulda","last_name":"Haselgrove","email":"hhaselgrove1h@digg.com"},
{"first_name":"Stephani","last_name":"Carlyle","email":"scarlyle1i@abc.net.au"},
{"first_name":"Grover","last_name":"Tunnah","email":"gtunnah1j@de.vu"},
{"first_name":"Dionne","last_name":"Foulstone","email":"dfoulstone1k@taobao.com"},
{"first_name":"Avigdor","last_name":"Deerness","email":"adeerness1l@go.com"},
{"first_name":"Griz","last_name":"Sherborne","email":"gsherborne1m@51.la"},
{"first_name":"Forster","last_name":"Kuscha","email":"fkuscha1n@disqus.com"},
{"first_name":"Mommy","last_name":"Wilfinger","email":"mwilfinger1o@tamu.edu"},
{"first_name":"Ruth","last_name":"Klimt","email":"rklimt1p@columbia.edu"},
{"first_name":"Kittie","last_name":"MacGeaney","email":"kmacgeaney1q@go.com"},
{"first_name":"Fionna","last_name":"De Minico","email":"fdeminico1r@marriott.com"},
{"first_name":"Brena","last_name":"Heading","email":"bheading1s@cnn.com"},
{"first_name":"Aldin","last_name":"Minghi","email":"aminghi1t@mashable.com"},
{"first_name":"Ulla","last_name":"Elverston","email":"uelverston1u@miitbeian.gov.cn"},
{"first_name":"Catharina","last_name":"Romanelli","email":"cromanelli1v@nifty.com"},
{"first_name":"Coralie","last_name":"Sollon","email":"csollon1w@weather.com"},
{"first_name":"Elvina","last_name":"Ivan","email":"eivan1x@senate.gov"},
{"first_name":"Alfons","last_name":"Reddle","email":"areddle1y@sakura.ne.jp"},
{"first_name":"Lucia","last_name":"Moneti","email":"lmoneti1z@ebay.co.uk"},
{"first_name":"Ellynn","last_name":"De Cleen","email":"edecleen20@epa.gov"},
{"first_name":"Mellie","last_name":"Ellwell","email":"mellwell21@1688.com"},
{"first_name":"Priscella","last_name":"Simenet","email":"psimenet22@nytimes.com"},
{"first_name":"Ermin","last_name":"Gallelli","email":"egallelli23@ning.com"},
{"first_name":"Georgetta","last_name":"Ibbitson","email":"gibbitson24@examiner.com"},
{"first_name":"Jerrie","last_name":"Gristwood","email":"jgristwood25@time.com"},
{"first_name":"Guillermo","last_name":"Benini","email":"gbenini26@nydailynews.com"},
{"first_name":"Cathie","last_name":"Mateiko","email":"cmateiko27@gravatar.com"},
{"first_name":"Royal","last_name":"Jachtym","email":"rjachtym28@eepurl.com"},
{"first_name":"Ettie","last_name":"Coultish","email":"ecoultish29@privacy.gov.au"},
{"first_name":"Sela","last_name":"Kohn","email":"skohn2a@dmoz.org"},
{"first_name":"Laure","last_name":"Mogenot","email":"lmogenot2b@aol.com"},
{"first_name":"Fowler","last_name":"Sharram","email":"fsharram2c@hostgator.com"},
{"first_name":"Brannon","last_name":"De Avenell","email":"bdeavenell2d@cocolog-nifty.com"},
{"first_name":"Symon","last_name":"Bowring","email":"sbowring2e@flavors.me"},
{"first_name":"Ronica","last_name":"Coger","email":"rcoger2f@digg.com"},
{"first_name":"Kelli","last_name":"Craigg","email":"kcraigg2g@deviantart.com"},
{"first_name":"Colline","last_name":"Brundrett","email":"cbrundrett2h@slashdot.org"},
{"first_name":"Inga","last_name":"Ivey","email":"iivey2i@ftc.gov"},
{"first_name":"Bettine","last_name":"Abramow","email":"babramow2j@google.co.uk"},
{"first_name":"Lemmy","last_name":"Medgewick","email":"lmedgewick2k@ucsd.edu"},
{"first_name":"Julee","last_name":"Buddles","email":"jbuddles2l@barnesandnoble.com"},
{"first_name":"Hendrick","last_name":"Paquet","email":"hpaquet2m@php.net"},
{"first_name":"Sigfrid","last_name":"Phebee","email":"sphebee2n@squarespace.com"},
{"first_name":"Minnaminnie","last_name":"Braiden","email":"mbraiden2o@unesco.org"},
{"first_name":"Adeline","last_name":"Reame","email":"areame2p@simplemachines.org"},
{"first_name":"Chandra","last_name":"Cinavas","email":"ccinavas2q@cnbc.com"},
{"first_name":"Jabez","last_name":"Barnham","email":"jbarnham2r@yellowbook.com"}]